{"growth": "linear", "n_changepoints": 4, "specified_changepoints": false, "changepoint_range": 0.8, "yearly_seasonality": "auto", "weekly_seasonality": "auto", "daily_seasonality": "auto", "seasonality_mode": "additive", "seasonality_prior_scale": 10.0, "changepoint_prior_scale": 0.05, "holidays_prior_scale": 10.0, "mcmc_samples": 0, "interval_width": 0.8, "uncertainty_samples": 1000, "y_scale": 50.9655859069886, "logistic_floor": false, "country_holidays": null, "component_modes": {"additive": ["additive_terms", "extra_regressors_additive", "holidays"], "multiplicative": ["multiplicative_terms", "extra_regressors_multiplicative"]}, "changepoints": "{\"name\":\"ds\",\"index\":[1,2,3,4],\"data\":[\"2022-09-14T11:26:10.000Z\",\"2022-09-14T11:26:20.000Z\",\"2022-09-14T11:26:30.000Z\",\"2022-09-14T11:26:40.000Z\"]}", "history_dates": "{\"name\":\"ds\",\"index\":[0,1,2,3,4,5,6],\"data\":[\"2022-09-14T11:26:00.000Z\",\"2022-09-14T11:26:10.000Z\",\"2022-09-14T11:26:20.000Z\",\"2022-09-14T11:26:30.000Z\",\"2022-09-14T11:26:40.000Z\",\"2022-09-14T11:26:50.000Z\",\"2022-09-14T11:27:00.000Z\"]}", "train_holiday_names": null, "start": 1663154760.0, "t_scale": 60.0, "holidays": null, "history": "{\"schema\":{\"fields\":[{\"name\":\"Time\",\"type\":\"datetime\"},{\"name\":\"ds\",\"type\":\"datetime\"},{\"name\":\"y\",\"type\":\"number\"},{\"name\":\"floor\",\"type\":\"integer\"},{\"name\":\"t\",\"type\":\"number\"},{\"name\":\"y_scaled\",\"type\":\"number\"}],\"pandas_version\":\"0.20.0\"},\"data\":[{\"Time\":\"2022-09-14T11:26:00.000Z\",\"ds\":\"2022-09-14T11:26:00.000Z\",\"y\":50.7003276623,\"floor\":0,\"t\":0.0,\"y_scaled\":0.9947953459},{\"Time\":\"2022-09-14T11:26:10.000Z\",\"ds\":\"2022-09-14T11:26:10.000Z\",\"y\":50.5631916023,\"floor\":0,\"t\":0.1666666667,\"y_scaled\":0.9921045879},{\"Time\":\"2022-09-14T11:26:20.000Z\",\"ds\":\"2022-09-14T11:26:20.000Z\",\"y\":50.5915597884,\"floor\":0,\"t\":0.3333333333,\"y_scaled\":0.9926612024},{\"Time\":\"2022-09-14T11:26:30.000Z\",\"ds\":\"2022-09-14T11:26:30.000Z\",\"y\":50.3689630853,\"floor\":0,\"t\":0.5,\"y_scaled\":0.988293614},{\"Time\":\"2022-09-14T11:26:40.000Z\",\"ds\":\"2022-09-14T11:26:40.000Z\",\"y\":50.4346413594,\"floor\":0,\"t\":0.6666666667,\"y_scaled\":0.9895822929},{\"Time\":\"2022-09-14T11:26:50.000Z\",\"ds\":\"2022-09-14T11:26:50.000Z\",\"y\":50.6525134859,\"floor\":0,\"t\":0.8333333333,\"y_scaled\":0.99385718},{\"Time\":\"2022-09-14T11:27:00.000Z\",\"ds\":\"2022-09-14T11:27:00.000Z\",\"y\":50.965585907,\"floor\":0,\"t\":1.0,\"y_scaled\":1.0}]}", "train_component_cols": "{\"schema\":{\"fields\":[{\"name\":\"additive_terms\",\"type\":\"integer\"},{\"name\":\"multiplicative_terms\",\"type\":\"integer\"}],\"pandas_version\":\"0.20.0\"},\"data\":[{\"additive_terms\":0,\"multiplicative_terms\":0}]}", "changepoints_t": [0.16666666666666666, 0.3333333333333333, 0.5, 0.6666666666666666], "seasonalities": [[], {}], "extra_regressors": [[], {}], "fit_kwargs": {"init": {"k": -0.03197894987148837, "m": 0.9999932643599309, "sigma_obs": 0.00023677477151907078, "delta": [0.04680709045362657, -0.039776703399876594, 0.02162077966692174, 0.02181138091434653], "beta": [1.232671128664879e-14]}}, "params": {"k": [[-0.015904066932294486]], "m": [[0.9947853276155955]], "delta": [[0.018822925752066143, -0.02876366298959767, 0.03161875270402375, 0.025449100617959092]], "sigma_obs": [[0.0002890089234443943]], "beta": [[-2.8738734413509894e-15]], "trend": [[0.9947853276155955, 0.9921346497935464, 0.9926211262635083, 0.9883136589018706, 0.9892759836575703, 0.9944798251829298, 0.9996836667082891]]}, "__prophet_version": "1.0"}