{"growth": "linear", "n_changepoints": 10, "specified_changepoints": false, "changepoint_range": 0.8, "yearly_seasonality": "auto", "weekly_seasonality": "auto", "daily_seasonality": "auto", "seasonality_mode": "additive", "seasonality_prior_scale": 10.0, "changepoint_prior_scale": 0.05, "holidays_prior_scale": 10.0, "mcmc_samples": 0, "interval_width": 0.8, "uncertainty_samples": 1000, "y_scale": 33.39801177976321, "logistic_floor": false, "country_holidays": null, "component_modes": {"additive": ["additive_terms", "extra_regressors_additive", "holidays"], "multiplicative": ["multiplicative_terms", "extra_regressors_multiplicative"]}, "changepoints": "{\"name\":\"ds\",\"index\":[1,2,3,4,5,6,7,8,9,10],\"data\":[\"2022-09-10T07:02:15.000Z\",\"2022-09-10T07:02:30.000Z\",\"2022-09-10T07:02:45.000Z\",\"2022-09-10T07:03:00.000Z\",\"2022-09-10T07:03:15.000Z\",\"2022-09-10T07:03:30.000Z\",\"2022-09-10T07:03:45.000Z\",\"2022-09-10T07:04:00.000Z\",\"2022-09-10T07:04:15.000Z\",\"2022-09-10T07:04:30.000Z\"]}", "history_dates": "{\"name\":\"ds\",\"index\":[0,1,2,3,4,5,6,7,8,9,10,11,12,13],\"data\":[\"2022-09-10T07:02:00.000Z\",\"2022-09-10T07:02:15.000Z\",\"2022-09-10T07:02:30.000Z\",\"2022-09-10T07:02:45.000Z\",\"2022-09-10T07:03:00.000Z\",\"2022-09-10T07:03:15.000Z\",\"2022-09-10T07:03:30.000Z\",\"2022-09-10T07:03:45.000Z\",\"2022-09-10T07:04:00.000Z\",\"2022-09-10T07:04:15.000Z\",\"2022-09-10T07:04:30.000Z\",\"2022-09-10T07:04:45.000Z\",\"2022-09-10T07:05:00.000Z\",\"2022-09-10T07:05:15.000Z\"]}", "train_holiday_names": null, "start": 1662793320.0, "t_scale": 195.0, "holidays": null, "history": "{\"schema\":{\"fields\":[{\"name\":\"Time\",\"type\":\"datetime\"},{\"name\":\"ds\",\"type\":\"datetime\"},{\"name\":\"y\",\"type\":\"number\"},{\"name\":\"floor\",\"type\":\"integer\"},{\"name\":\"t\",\"type\":\"number\"},{\"name\":\"y_scaled\",\"type\":\"number\"}],\"pandas_version\":\"0.20.0\"},\"data\":[{\"Time\":\"2022-09-10T07:02:00.000Z\",\"ds\":\"2022-09-10T07:02:00.000Z\",\"y\":33.3980117798,\"floor\":0,\"t\":0.0,\"y_scaled\":1.0},{\"Time\":\"2022-09-10T07:02:15.000Z\",\"ds\":\"2022-09-10T07:02:15.000Z\",\"y\":33.3980117798,\"floor\":0,\"t\":0.0769230769,\"y_scaled\":1.0},{\"Time\":\"2022-09-10T07:02:30.000Z\",\"ds\":\"2022-09-10T07:02:30.000Z\",\"y\":33.3980117798,\"floor\":0,\"t\":0.1538461538,\"y_scaled\":1.0},{\"Time\":\"2022-09-10T07:02:45.000Z\",\"ds\":\"2022-09-10T07:02:45.000Z\",\"y\":33.3980117798,\"floor\":0,\"t\":0.2307692308,\"y_scaled\":1.0},{\"Time\":\"2022-09-10T07:03:00.000Z\",\"ds\":\"2022-09-10T07:03:00.000Z\",\"y\":33.3980117798,\"floor\":0,\"t\":0.3076923077,\"y_scaled\":1.0},{\"Time\":\"2022-09-10T07:03:15.000Z\",\"ds\":\"2022-09-10T07:03:15.000Z\",\"y\":33.3980117798,\"floor\":0,\"t\":0.3846153846,\"y_scaled\":1.0},{\"Time\":\"2022-09-10T07:03:30.000Z\",\"ds\":\"2022-09-10T07:03:30.000Z\",\"y\":33.3980117798,\"floor\":0,\"t\":0.4615384615,\"y_scaled\":1.0},{\"Time\":\"2022-09-10T07:03:45.000Z\",\"ds\":\"2022-09-10T07:03:45.000Z\",\"y\":33.3980117798,\"floor\":0,\"t\":0.5384615385,\"y_scaled\":1.0},{\"Time\":\"2022-09-10T07:04:00.000Z\",\"ds\":\"2022-09-10T07:04:00.000Z\",\"y\":33.3980117798,\"floor\":0,\"t\":0.6153846154,\"y_scaled\":1.0},{\"Time\":\"2022-09-10T07:04:15.000Z\",\"ds\":\"2022-09-10T07:04:15.000Z\",\"y\":33.3980117798,\"floor\":0,\"t\":0.6923076923,\"y_scaled\":1.0},{\"Time\":\"2022-09-10T07:04:30.000Z\",\"ds\":\"2022-09-10T07:04:30.000Z\",\"y\":33.3980117798,\"floor\":0,\"t\":0.7692307692,\"y_scaled\":1.0},{\"Time\":\"2022-09-10T07:04:45.000Z\",\"ds\":\"2022-09-10T07:04:45.000Z\",\"y\":33.3980117798,\"floor\":0,\"t\":0.8461538462,\"y_scaled\":1.0},{\"Time\":\"2022-09-10T07:05:00.000Z\",\"ds\":\"2022-09-10T07:05:00.000Z\",\"y\":33.3980117798,\"floor\":0,\"t\":0.9230769231,\"y_scaled\":1.0},{\"Time\":\"2022-09-10T07:05:15.000Z\",\"ds\":\"2022-09-10T07:05:15.000Z\",\"y\":33.3980117798,\"floor\":0,\"t\":1.0,\"y_scaled\":1.0}]}", "train_component_cols": "{\"schema\":{\"fields\":[{\"name\":\"additive_terms\",\"type\":\"integer\"},{\"name\":\"multiplicative_terms\",\"type\":\"integer\"}],\"pandas_version\":\"0.20.0\"},\"data\":[{\"additive_terms\":0,\"multiplicative_terms\":0}]}", "changepoints_t": [0.07692307692307693, 0.15384615384615385, 0.23076923076923078, 0.3076923076923077, 0.38461538461538464, 0.46153846153846156, 0.5384615384615384, 0.6153846153846154, 0.6923076923076923, 0.7692307692307693], "seasonalities": [[], {}], "extra_regressors": [[], {}], "fit_kwargs": {}, "params": {"k": [0.0], "m": [1.0], "delta": [[0.0, 0.0, 0.0, 0.0, 0.0, 0.0, 0.0, 0.0, 0.0, 0.0]], "beta": [[0.0]], "sigma_obs": [1e-09]}, "__prophet_version": "1.0"}